{"ref":"46e22f50-d375-4ce5-9206-04de043acfbb","syncData":{"version":5,"machineId":"89f849d0-2193-403d-8b95-e79e53d196bc","content":"[{\"identifier\":{\"id\":\"vscode.bat\"},\"version\":\"1.0.0\",\"preRelease\":false,\"pinned\":false},{\"identifier\":{\"id\":\"vscode.clojure\"},\"version\":\"1.0.0\",\"preRelease\":false,\"pinned\":false},{\"identifier\":{\"id\":\"vscode.coffeescript\"},\"version\":\"1.0.0\",\"preRelease\":false,\"pinned\":false},{\"identifier\":{\"id\":\"vscode.configuration-editing\"},\"version\":\"1.0.0\",\"preRelease\":false,\"pinned\":false},{\"identifier\":{\"id\":\"vscode.cpp\"},\"version\":\"1.0.0\",\"preRelease\":false,\"pinned\":false},{\"identifier\":{\"id\":\"vscode.csharp\"},\"version\":\"1.0.0\",\"preRelease\":false,\"pinned\":false},{\"identifier\":{\"id\":\"vscode.css\"},\"version\":\"1.0.0\",\"preRelease\":false,\"pinned\":false},{\"identifier\":{\"id\":\"vscode.css-language-features\"},\"version\":\"1.0.0\",\"preRelease\":false,\"pinned\":false},{\"identifier\":{\"id\":\"vscode.debug-auto-launch\"},\"version\":\"1.0.0\",\"preRelease\":false,\"pinned\":false},{\"identifier\":{\"id\":\"vscode.debug-server-ready\"},\"version\":\"1.0.0\",\"preRelease\":false,\"pinned\":false},{\"identifier\":{\"id\":\"vscode.docker\"},\"version\":\"1.0.0\",\"preRelease\":false,\"pinned\":false},{\"identifier\":{\"id\":\"vscode.emmet\"},\"version\":\"1.0.0\",\"preRelease\":false,\"pinned\":false},{\"identifier\":{\"id\":\"vscode.extension-editing\"},\"version\":\"1.0.0\",\"preRelease\":false,\"pinned\":false},{\"identifier\":{\"id\":\"vscode.fsharp\"},\"version\":\"1.0.0\",\"preRelease\":false,\"pinned\":false},{\"identifier\":{\"id\":\"vscode.git\"},\"version\":\"1.0.0\",\"preRelease\":false,\"pinned\":false},{\"identifier\":{\"id\":\"vscode.git-ui\"},\"version\":\"1.0.0\",\"preRelease\":false,\"pinned\":false},{\"identifier\":{\"id\":\"vscode.github\"},\"version\":\"0.0.1\",\"preRelease\":false,\"pinned\":false},{\"identifier\":{\"id\":\"vscode.github-authentication\"},\"version\":\"0.0.1\",\"preRelease\":false,\"pinned\":false},{\"identifier\":{\"id\":\"vscode.go\"},\"version\":\"1.0.0\",\"preRelease\":false,\"pinned\":false},{\"identifier\":{\"id\":\"vscode.groovy\"},\"version\":\"1.0.0\",\"preRelease\":false,\"pinned\":false},{\"identifier\":{\"id\":\"vscode.grunt\"},\"version\":\"1.0.0\",\"preRelease\":false,\"pinned\":false},{\"identifier\":{\"id\":\"vscode.gulp\"},\"version\":\"1.0.0\",\"preRelease\":false,\"pinned\":false},{\"identifier\":{\"id\":\"vscode.handlebars\"},\"version\":\"1.0.0\",\"preRelease\":false,\"pinned\":false},{\"identifier\":{\"id\":\"vscode.hlsl\"},\"version\":\"1.0.0\",\"preRelease\":false,\"pinned\":false},{\"identifier\":{\"id\":\"vscode.html\"},\"version\":\"1.0.0\",\"preRelease\":false,\"pinned\":false},{\"identifier\":{\"id\":\"vscode.html-language-features\"},\"version\":\"1.0.0\",\"preRelease\":false,\"pinned\":false},{\"identifier\":{\"id\":\"vscode.image-preview\"},\"version\":\"1.0.0\",\"preRelease\":false,\"pinned\":false},{\"identifier\":{\"id\":\"vscode.ini\"},\"version\":\"1.0.0\",\"preRelease\":false,\"pinned\":false},{\"identifier\":{\"id\":\"vscode.jake\"},\"version\":\"1.0.0\",\"preRelease\":false,\"pinned\":false},{\"identifier\":{\"id\":\"vscode.java\"},\"version\":\"1.0.0\",\"preRelease\":false,\"pinned\":false},{\"identifier\":{\"id\":\"vscode.javascript\"},\"version\":\"1.0.0\",\"preRelease\":false,\"pinned\":false},{\"identifier\":{\"id\":\"vscode.json\"},\"version\":\"1.0.0\",\"preRelease\":false,\"pinned\":false},{\"identifier\":{\"id\":\"vscode.json-language-features\"},\"version\":\"1.0.0\",\"preRelease\":false,\"pinned\":false},{\"identifier\":{\"id\":\"vscode.less\"},\"version\":\"1.0.0\",\"preRelease\":false,\"pinned\":false},{\"identifier\":{\"id\":\"vscode.log\"},\"version\":\"1.0.0\",\"preRelease\":false,\"pinned\":false},{\"identifier\":{\"id\":\"vscode.lua\"},\"version\":\"1.0.0\",\"preRelease\":false,\"pinned\":false},{\"identifier\":{\"id\":\"vscode.make\"},\"version\":\"1.0.0\",\"preRelease\":false,\"pinned\":false},{\"identifier\":{\"id\":\"vscode.markdown\"},\"version\":\"1.0.0\",\"preRelease\":false,\"pinned\":false},{\"identifier\":{\"id\":\"vscode.markdown-language-features\"},\"version\":\"1.0.0\",\"preRelease\":false,\"pinned\":false},{\"identifier\":{\"id\":\"vscode.merge-conflict\"},\"version\":\"1.0.0\",\"preRelease\":false,\"pinned\":false},{\"identifier\":{\"id\":\"vscode.microsoft-authentication\"},\"version\":\"0.0.1\",\"preRelease\":false,\"pinned\":false},{\"identifier\":{\"id\":\"ms-vscode.js-debug\",\"uuid\":\"25629058-ddac-4e17-abba-74678e126c5d\"},\"version\":\"1.51.0\",\"preRelease\":false,\"pinned\":false},{\"identifier\":{\"id\":\"ms-vscode.js-debug-companion\",\"uuid\":\"99cb0b7f-7354-4278-b8da-6cc79972169d\"},\"version\":\"1.0.8\",\"preRelease\":false,\"pinned\":false},{\"identifier\":{\"id\":\"ms-vscode.node-debug\",\"uuid\":\"b6ded8fb-a0a0-4c1c-acbd-ab2a3bc995a6\"},\"version\":\"1.44.14\",\"preRelease\":false,\"pinned\":false},{\"identifier\":{\"id\":\"ms-vscode.node-debug2\",\"uuid\":\"36d19e17-7569-4841-a001-947eb18602b2\"},\"version\":\"1.42.5\",\"preRelease\":false,\"pinned\":false},{\"identifier\":{\"id\":\"ms-vscode.references-view\",\"uuid\":\"dc489f46-520d-4556-ae85-1f9eab3c412d\"},\"version\":\"0.0.71\",\"preRelease\":false,\"pinned\":false},{\"identifier\":{\"id\":\"ms-vscode.vscode-js-profile-table\",\"uuid\":\"7e52b41b-71ad-457b-ab7e-0620f1fc4feb\"},\"version\":\"0.0.11\",\"preRelease\":false,\"pinned\":false},{\"identifier\":{\"id\":\"vscode.npm\"},\"version\":\"1.0.1\",\"preRelease\":false,\"pinned\":false},{\"identifier\":{\"id\":\"vscode.objective-c\"},\"version\":\"1.0.0\",\"preRelease\":false,\"pinned\":false},{\"identifier\":{\"id\":\"vscode.perl\"},\"version\":\"1.0.0\",\"preRelease\":false,\"pinned\":false},{\"identifier\":{\"id\":\"vscode.php\"},\"version\":\"1.0.0\",\"preRelease\":false,\"pinned\":false},{\"identifier\":{\"id\":\"vscode.php-language-features\"},\"version\":\"1.0.0\",\"preRelease\":false,\"pinned\":false},{\"identifier\":{\"id\":\"vscode.powershell\"},\"version\":\"1.0.0\",\"preRelease\":false,\"pinned\":false},{\"identifier\":{\"id\":\"vscode.pug\"},\"version\":\"1.0.0\",\"preRelease\":false,\"pinned\":false},{\"identifier\":{\"id\":\"vscode.python\"},\"version\":\"1.0.0\",\"preRelease\":false,\"pinned\":false},{\"identifier\":{\"id\":\"vscode.r\"},\"version\":\"1.0.0\",\"preRelease\":false,\"pinned\":false},{\"identifier\":{\"id\":\"vscode.razor\"},\"version\":\"1.0.0\",\"preRelease\":false,\"pinned\":false},{\"identifier\":{\"id\":\"vscode.ruby\"},\"version\":\"1.0.0\",\"preRelease\":false,\"pinned\":false},{\"identifier\":{\"id\":\"vscode.rust\"},\"version\":\"1.0.0\",\"preRelease\":false,\"pinned\":false},{\"identifier\":{\"id\":\"vscode.scss\"},\"version\":\"1.0.0\",\"preRelease\":false,\"pinned\":false},{\"identifier\":{\"id\":\"vscode.search-result\"},\"version\":\"1.0.0\",\"preRelease\":false,\"pinned\":false},{\"identifier\":{\"id\":\"vscode.shaderlab\"},\"version\":\"1.0.0\",\"preRelease\":false,\"pinned\":false},{\"identifier\":{\"id\":\"vscode.shellscript\"},\"version\":\"1.0.0\",\"preRelease\":false,\"pinned\":false},{\"identifier\":{\"id\":\"vscode.sql\"},\"version\":\"1.0.0\",\"preRelease\":false,\"pinned\":false},{\"identifier\":{\"id\":\"vscode.swift\"},\"version\":\"1.0.0\",\"preRelease\":false,\"pinned\":false},{\"identifier\":{\"id\":\"vscode.theme-abyss\"},\"version\":\"1.0.0\",\"preRelease\":false,\"pinned\":false},{\"identifier\":{\"id\":\"vscode.theme-defaults\"},\"version\":\"1.0.0\",\"preRelease\":false,\"pinned\":false},{\"identifier\":{\"id\":\"vscode.theme-kimbie-dark\"},\"version\":\"1.0.0\",\"preRelease\":false,\"pinned\":false},{\"identifier\":{\"id\":\"vscode.theme-monokai\"},\"version\":\"1.0.0\",\"preRelease\":false,\"pinned\":false},{\"identifier\":{\"id\":\"vscode.theme-monokai-dimmed\"},\"version\":\"1.0.0\",\"preRelease\":false,\"pinned\":false},{\"identifier\":{\"id\":\"vscode.theme-quietlight\"},\"version\":\"1.0.0\",\"preRelease\":false,\"pinned\":false},{\"identifier\":{\"id\":\"vscode.theme-red\"},\"version\":\"1.0.0\",\"preRelease\":false,\"pinned\":false},{\"identifier\":{\"id\":\"vscode.vscode-theme-seti\"},\"version\":\"1.0.0\",\"preRelease\":false,\"pinned\":false},{\"identifier\":{\"id\":\"vscode.theme-solarized-dark\"},\"version\":\"1.0.0\",\"preRelease\":false,\"pinned\":false},{\"identifier\":{\"id\":\"vscode.theme-solarized-light\"},\"version\":\"1.0.0\",\"preRelease\":false,\"pinned\":false},{\"identifier\":{\"id\":\"vscode.theme-tomorrow-night-blue\"},\"version\":\"1.0.0\",\"preRelease\":false,\"pinned\":false},{\"identifier\":{\"id\":\"vscode.typescript\"},\"version\":\"1.0.0\",\"preRelease\":false,\"pinned\":false},{\"identifier\":{\"id\":\"vscode.typescript-language-features\"},\"version\":\"1.0.0\",\"preRelease\":false,\"pinned\":false},{\"identifier\":{\"id\":\"vscode.vb\"},\"version\":\"1.0.0\",\"preRelease\":false,\"pinned\":false},{\"identifier\":{\"id\":\"vscode.xml\"},\"version\":\"1.0.0\",\"preRelease\":false,\"pinned\":false},{\"identifier\":{\"id\":\"vscode.yaml\"},\"version\":\"1.0.0\",\"preRelease\":false,\"pinned\":false},{\"identifier\":{\"id\":\"golang.go\",\"uuid\":\"d6f6cfea-4b6f-41f4-b571-6ad2ab7918da\"},\"version\":\"0.32.0\",\"preRelease\":false,\"pinned\":false,\"installed\":true},{\"identifier\":{\"id\":\"ms-python.anaconda-extension-pack\",\"uuid\":\"5a8b9107-e667-4ec8-a792-d066a93b9eff\"},\"version\":\"1.0.1\",\"preRelease\":false,\"pinned\":false,\"installed\":true},{\"identifier\":{\"id\":\"ms-python.python\",\"uuid\":\"f1f59ae4-9318-4f3c-a9b5-81b2eaa5f8a5\"},\"version\":\"2021.10.1365161279\",\"preRelease\":false,\"pinned\":false,\"installed\":true},{\"identifier\":{\"id\":\"ms-vscode-remote.remote-containers\",\"uuid\":\"93ce222b-5f6f-49b7-9ab1-a0463c6238df\"},\"version\":\"0.187.1\",\"preRelease\":false,\"pinned\":false,\"installed\":true,\"state\":{}},{\"identifier\":{\"id\":\"ms-vscode-remote.remote-ssh\",\"uuid\":\"607fd052-be03-4363-b657-2bd62b83d28a\"},\"version\":\"0.66.0\",\"preRelease\":false,\"pinned\":false,\"installed\":true},{\"identifier\":{\"id\":\"ms-vscode-remote.remote-ssh-edit\",\"uuid\":\"bfeaf631-bcff-4908-93ed-fda4ef9a0c5c\"},\"version\":\"0.65.8\",\"preRelease\":false,\"pinned\":false,\"installed\":true},{\"identifier\":{\"id\":\"ms-vscode-remote.remote-wsl\",\"uuid\":\"f0c5397b-d357-4197-99f0-cb4202f22818\"},\"version\":\"0.58.5\",\"preRelease\":false,\"pinned\":false,\"installed\":true},{\"identifier\":{\"id\":\"ms-vscode-remote.vscode-remote-extensionpack\",\"uuid\":\"23d72dfc-8dd1-4e30-926e-8783b4378f13\"},\"version\":\"0.21.0\",\"preRelease\":false,\"pinned\":false,\"installed\":true},{\"identifier\":{\"id\":\"redhat.vscode-yaml\",\"uuid\":\"2061917f-f76a-458a-8da9-f162de22b97e\"},\"version\":\"1.6.0\",\"preRelease\":false,\"pinned\":false,\"installed\":true},{\"identifier\":{\"id\":\"mechatroner.rainbow-csv\",\"uuid\":\"3792588c-3d35-442d-91ea-fe6a755e8155\"},\"version\":\"3.7.0\",\"preRelease\":false,\"pinned\":false,\"installed\":true},{\"identifier\":{\"id\":\"ms-toolsai.jupyter\",\"uuid\":\"6c2f1801-1e7f-45b2-9b5c-7782f1e076e8\"},\"version\":\"2021.8.1054968649\",\"preRelease\":false,\"pinned\":false,\"installed\":true},{\"identifier\":{\"id\":\"vscode.julia\"},\"version\":\"1.0.0\",\"preRelease\":false,\"pinned\":false},{\"identifier\":{\"id\":\"ms-vscode-remote.remote-wsl-recommender\",\"uuid\":\"cb296d3c-017a-4dee-83af-ebb5a5a16e9a\"},\"version\":\"0.0.5\",\"preRelease\":false,\"pinned\":false},{\"identifier\":{\"id\":\"vscode.notebook-markdown-extensions\"},\"version\":\"1.0.0\",\"preRelease\":false,\"pinned\":false},{\"identifier\":{\"id\":\"vscode.simple-browser\"},\"version\":\"1.0.0\",\"preRelease\":false,\"pinned\":false},{\"identifier\":{\"id\":\"vscode.testing-editor-contributions\"},\"version\":\"1.0.0\",\"preRelease\":false,\"pinned\":false},{\"identifier\":{\"id\":\"vscode.dart\"},\"version\":\"1.0.0\",\"preRelease\":false,\"pinned\":false},{\"identifier\":{\"id\":\"ms-python.vscode-pylance\",\"uuid\":\"364d2426-116a-433a-a5d8-a5098dc3afbd\"},\"version\":\"2022.1.3\",\"preRelease\":false,\"pinned\":false,\"installed\":true},{\"identifier\":{\"id\":\"vscode.markdown-math\"},\"version\":\"1.0.0\",\"preRelease\":false,\"pinned\":false},{\"identifier\":{\"id\":\"vscode.ipynb\"},\"version\":\"1.0.0\",\"preRelease\":false,\"pinned\":false},{\"identifier\":{\"id\":\"vscode.diff\"},\"version\":\"1.0.0\",\"preRelease\":false,\"pinned\":false},{\"identifier\":{\"id\":\"vscode.git-base\"},\"version\":\"1.0.0\",\"preRelease\":false,\"pinned\":false},{\"identifier\":{\"id\":\"vscode.latex\"},\"version\":\"1.0.0\",\"preRelease\":false,\"pinned\":false},{\"identifier\":{\"id\":\"vscode.builtin-notebook-renderers\"},\"version\":\"1.0.0\",\"preRelease\":false,\"pinned\":false},{\"identifier\":{\"id\":\"vscode.restructuredtext\"},\"version\":\"1.0.0\",\"preRelease\":false,\"pinned\":false},{\"identifier\":{\"id\":\"ms-toolsai.jupyter-keymap\",\"uuid\":\"9f6dc8db-620c-4844-b8c5-e74914f1be27\"},\"version\":\"1.0.0\",\"preRelease\":false,\"pinned\":false,\"installed\":true},{\"identifier\":{\"id\":\"ms-toolsai.jupyter-renderers\",\"uuid\":\"b15c72f8-d5fe-421a-a4f7-27ed9f6addbf\"},\"version\":\"1.0.6\",\"preRelease\":false,\"pinned\":false,\"installed\":true},{\"identifier\":{\"id\":\"vscode.references-view\"},\"version\":\"1.0.0\",\"preRelease\":false,\"pinned\":false},{\"identifier\":{\"id\":\"vscode.media-preview\"},\"version\":\"1.0.0\",\"preRelease\":false,\"pinned\":false}]"}}